image2html/__init__.py
image2html/flist.py
image2html/html_generator.py
image2html/image2html.py
image2html-0.0.6.dist-info/LICENSE
image2html-0.0.6.dist-info/METADATA
image2html-0.0.6.dist-info/WHEEL
image2html-0.0.6.dist-info/entry_points.txt
image2html-0.0.6.dist-info/top_level.txt
image2html-0.0.6.dist-info/RECORD
