Metadata-Version: 2.1
Name: image2html
Version: 0.0.6
Summary: Display images with html file.
Home-page: https://github.com/ZQPei/image2html
Author: ZQPei
Author-email: peiziqiang@gmail.com
License: MIT
Platform: all
Requires-Dist: huster
Requires-Dist: numpy
Requires-Dist: dominate
